{
    "teams": [
        {
            "id": 1,
            "name": "Brasil",
            "description": "",
            "created-by": "_",
            "founded-in": "2023",
            "logo": "brasil.png"
        },
        {
            "id": 2,
            "name": "Espanha",
            "description": "",
            "created-by": "_",
            "founded-in": "2023",
            "logo": "espanha.png"
        },
        {
            "id": 3,
            "name": "Holanda",
            "description": "",
            "created-by": "",
            "founded-in": "",
            "logo": "holanda.png"
        },
        {
            "id": 4,
            "name": "Marrocos",
            "description": "",
            "created-by": "",
            "founded-in": "",
            "logo": "marrocos.png"
        },
        {
            "id": 5,
            "name": "Portugal",
            "description": "",
            "created-by": "",
            "founded-in": "",
            "logo": "portugal.png"
        },
        {
            "id": 6,
            "name": "Argentina",
            "description": "",
            "created-by": "",
            "founded-in": "",
            "logo": "argentina.png"
        },
        {
            "id": 7,
            "name": "França",
            "description": "",
            "created-by": "",
            "founded-in": "",
            "logo": "franca.png"
        },
        {
            "id": 8,
            "name": "Inglaterra",
            "description": "",
            "created-by": "",
            "founded-in": "",
            "logo": "inglaterra.png"
        }
    ]
}